videoinstruct/__init__.py
videoinstruct/configs.py
videoinstruct/prompt_loader.py
videoinstruct/videoinstructor.py
videoinstruct/agents/DocEvaluator.py
videoinstruct/agents/DocGenerator.py
videoinstruct/agents/ScreenshotAgent.py
videoinstruct/agents/VideoInterpreter.py
videoinstruct/agents/__init__.py
videoinstruct/prompts/doc_evaluator.txt
videoinstruct/prompts/doc_generator.txt
videoinstruct/prompts/screenshot_agent.txt
videoinstruct/tools/__init__.py
videoinstruct/tools/image_annotator.py
videoinstruct/tools/video_screenshot.py
videoinstruct/utils/__init__.py
videoinstruct/utils/md2pdf.py
videoinstruct/utils/transcription.py
videoinstruct-0.1.9.dist-info/LICENSE
videoinstruct-0.1.9.dist-info/METADATA
videoinstruct-0.1.9.dist-info/WHEEL
videoinstruct-0.1.9.dist-info/entry_points.txt
videoinstruct-0.1.9.dist-info/top_level.txt
videoinstruct-0.1.9.dist-info/RECORD
