Metadata-Version: 2.2
Name: videoinstruct
Version: 0.1.9
Summary: A tool that automatically generates step-by-step documentation from instructional videos
Home-page: https://github.com/PouriaRouzrokh/VideoInstruct
Author: Pouria Rouzrokh
Author-email: po.rouzrokh@gmail.com
Classifier: Programming Language :: Python :: 3
Classifier: License :: OSI Approved :: MIT License
Classifier: Operating System :: OS Independent
Requires-Python: >=3.8
License-File: LICENSE
Requires-Dist: python-dotenv==1.0.1
Requires-Dist: pydantic==2.10.6
Requires-Dist: markdown==3.7
Requires-Dist: litellm==1.61.16
Requires-Dist: google-generativeai==0.8.4
Requires-Dist: google-genai==1.3.0
Requires-Dist: openai==1.63.2
Requires-Dist: tiktoken==0.9.0
Requires-Dist: moviepy==2.1.2
Requires-Dist: pillow<11.0.0
Requires-Dist: opencv-python==4.11.0.86
Requires-Dist: numpy==1.26.4
Requires-Dist: xhtml2pdf==0.2.17
Requires-Dist: reportlab==4.3.1
Requires-Dist: tqdm==4.67.1
Dynamic: author
Dynamic: author-email
Dynamic: classifier
Dynamic: description
Dynamic: description-content-type
Dynamic: home-page
Dynamic: requires-dist
Dynamic: requires-python
Dynamic: summary
